odoo8_addon_partner_auto_salesman-8.0.1.0.0.99.dev7-py2.7-nspkg.pth
odoo8_addon_partner_auto_salesman-8.0.1.0.0.99.dev7.dist-info/DESCRIPTION.rst
odoo8_addon_partner_auto_salesman-8.0.1.0.0.99.dev7.dist-info/METADATA
odoo8_addon_partner_auto_salesman-8.0.1.0.0.99.dev7.dist-info/RECORD
odoo8_addon_partner_auto_salesman-8.0.1.0.0.99.dev7.dist-info/WHEEL
odoo8_addon_partner_auto_salesman-8.0.1.0.0.99.dev7.dist-info/metadata.json
odoo8_addon_partner_auto_salesman-8.0.1.0.0.99.dev7.dist-info/namespace_packages.txt
odoo8_addon_partner_auto_salesman-8.0.1.0.0.99.dev7.dist-info/top_level.txt
odoo_addons/partner_auto_salesman/__init__.py
odoo_addons/partner_auto_salesman/__openerp__.py
odoo_addons/partner_auto_salesman/res_partner.py
odoo_addons/partner_auto_salesman/i18n/de.po
odoo_addons/partner_auto_salesman/i18n/es.po
odoo_addons/partner_auto_salesman/i18n/eu.po
odoo_addons/partner_auto_salesman/i18n/fi.po
odoo_addons/partner_auto_salesman/i18n/it.po
odoo_addons/partner_auto_salesman/i18n/nl.po
odoo_addons/partner_auto_salesman/i18n/partner_auto_salesman.pot
odoo_addons/partner_auto_salesman/i18n/pt_BR.po
odoo_addons/partner_auto_salesman/i18n/sl.po
odoo_addons/partner_auto_salesman/static/description/icon.png
